steganogan/__init__.py
steganogan/cli.py
steganogan/critics.py
steganogan/decoders.py
steganogan/encoders.py
steganogan/loader.py
steganogan/models.py
steganogan/utils.py
steganogan/pretrained/basic.steg
steganogan/pretrained/dense.steg
steganogan/pretrained/residual.steg
steganogan-0.1.3.dist-info/AUTHORS.rst
steganogan-0.1.3.dist-info/LICENSE
steganogan-0.1.3.dist-info/METADATA
steganogan-0.1.3.dist-info/WHEEL
steganogan-0.1.3.dist-info/entry_points.txt
steganogan-0.1.3.dist-info/top_level.txt
steganogan-0.1.3.dist-info/RECORD
