Metadata-Version: 2.1
Name: steganogan
Version: 0.1.3
Summary: Steganography tool based on DeepLearning GANs
Home-page: https://github.com/DAI-Lab/SteganoGAN
Author: MIT Data To AI Lab
Author-email: dailabmit@gmail.com
License: MIT license
Keywords: steganogan
Platform: UNKNOWN
Classifier: Development Status :: 2 - Pre-Alpha
Classifier: Intended Audience :: Developers
Classifier: License :: OSI Approved :: MIT License
Classifier: Natural Language :: English
Classifier: Programming Language :: Python :: 3
Classifier: Programming Language :: Python :: 3.5
Classifier: Programming Language :: Python :: 3.6
Classifier: Programming Language :: Python :: 3.7
Requires-Python: >=3.5
Requires-Dist: imageio (<2.5.0,>=2.4.1)
Requires-Dist: reedsolo (==0.3)
Requires-Dist: scipy (<1.2.0,>=1.1.0)
Requires-Dist: tqdm (>=4.28.1)
Requires-Dist: numpy (>=1.15.4<1.16.0)
Requires-Dist: Pillow (<7.0.0,>=5.0.0)
Requires-Dist: torch (==1.0.0)
Requires-Dist: torchvision (==0.2.1)
Provides-Extra: dev
Requires-Dist: pip (>=9.0.1) ; extra == 'dev'
Requires-Dist: bumpversion (<0.6,>=0.5.3) ; extra == 'dev'
Requires-Dist: watchdog (<0.11,>=0.8.3) ; extra == 'dev'
Requires-Dist: m2r (<0.3,>=0.2.0) ; extra == 'dev'
Requires-Dist: Sphinx (<3,>=1.7.1) ; extra == 'dev'
Requires-Dist: sphinx-rtd-theme (<0.5,>=0.2.4) ; extra == 'dev'
Requires-Dist: flake8 (<4,>=3.7.7) ; extra == 'dev'
Requires-Dist: isort (<5,>=4.3.4) ; extra == 'dev'
Requires-Dist: autoflake (<2,>=1.1) ; extra == 'dev'
Requires-Dist: autopep8 (<2,>=1.4.3) ; extra == 'dev'
Requires-Dist: twine (<4,>=1.10.0) ; extra == 'dev'
Requires-Dist: wheel (>=0.30.0) ; extra == 'dev'
Requires-Dist: coverage (<6,>=4.5.1) ; extra == 'dev'
Requires-Dist: tox (<4,>=2.9.1) ; extra == 'dev'
Requires-Dist: jupyter (<2,>=1.0.0) ; extra == 'dev'
Requires-Dist: pytest (>=3.4.2) ; extra == 'dev'
Requires-Dist: pytest-cov (>=2.6.0) ; extra == 'dev'
Provides-Extra: test
Requires-Dist: pytest (>=3.4.2) ; extra == 'test'
Requires-Dist: pytest-cov (>=2.6.0) ; extra == 'test'
